MANIFEST.in
README.md
setup.cfg
setup.py
Flask_SQLAlchemy_Booster.egg-info/PKG-INFO
Flask_SQLAlchemy_Booster.egg-info/SOURCES.txt
Flask_SQLAlchemy_Booster.egg-info/dependency_links.txt
Flask_SQLAlchemy_Booster.egg-info/requires.txt
Flask_SQLAlchemy_Booster.egg-info/top_level.txt
flask_sqlalchemy_booster/__init__.py
flask_sqlalchemy_booster/core.py
flask_sqlalchemy_booster/custom_collections.py
flask_sqlalchemy_booster/flask_client_booster.py
flask_sqlalchemy_booster/interactive_shell.py
flask_sqlalchemy_booster/json_columns.py
flask_sqlalchemy_booster/json_encoder.py
flask_sqlalchemy_booster/query_booster.py
flask_sqlalchemy_booster/responses.py
flask_sqlalchemy_booster/schema_generators.py
flask_sqlalchemy_booster/utils.py
flask_sqlalchemy_booster/entities_router/__init__.py
flask_sqlalchemy_booster/entities_router/crud_constructors.py
flask_sqlalchemy_booster/entities_router/entity_definition_keys.py
flask_sqlalchemy_booster/model_booster/__init__.py
flask_sqlalchemy_booster/model_booster/dictizable_mixin.py
flask_sqlalchemy_booster/model_booster/queryable_mixin.py