Metadata-Version: 1.0
Name: Flask-SQLAlchemy-Booster
Version: 0.6.28
Summary: A booster package for Flask and SQLAlchemy
Home-page: https://github.com/SuryaSankar/flask-sqlalchemy-booster
Author: SuryaSankar
Author-email: suryashankar.m@gmail.com
License: MIT
Platform: UNKNOWN
